{
  "tdeck": {
    "version": "1.5.7",
    "url": "https://raw.githubusercontent.com/andymux/meshos-releases/main/firmware/MeshOS-TDeck-v1.5.7.bin",
    "size": 5167760,
    "sha256": "a96356b479cce107d6359546592a49e88a61782e0407e42ade909513fb47c25a",
    "notes": "WiFi cold-scan reliability fix and connect-dialog improvements. New map tools: drop a pin to navigate back to a saved spot, and show where the last mesh signal came from. JPG wallpaper support with large images and faster boot. Room server bug fixes."
  },
  "m9": {
    "version": "1.5.7",
    "url": "https://raw.githubusercontent.com/andymux/meshos-releases/main/firmware/MeshOS-M9-v1.5.7.bin",
    "size": 4746144,
    "sha256": "576925cf23254c60fa877a664116742302b4ca6d8f8474669124e1a3d5413a2d",
    "notes": "WiFi cold-scan reliability fix and connect-dialog improvements. New map tools: drop a pin to navigate back to a saved spot, and show where the last mesh signal came from. JPG wallpaper support with large images and faster boot. Room server bug fixes."
  }
}
